yppm/__init__.py
yppm/__main__.py
yppm/_todo.py
yppm/main.py
yppm/auto_everything/__init__.py
yppm/auto_everything/__main__.py
yppm/auto_everything/_command_line_interface.py
yppm/auto_everything/all.py
yppm/auto_everything/audio.py
yppm/auto_everything/base.py
yppm/auto_everything/camera.py
yppm/auto_everything/cryptography.py
yppm/auto_everything/database.py
yppm/auto_everything/develop.py
yppm/auto_everything/disk.py
yppm/auto_everything/gui.py
yppm/auto_everything/http_.py
yppm/auto_everything/humanity.py
yppm/auto_everything/image.py
yppm/auto_everything/io.py
yppm/auto_everything/language.py
yppm/auto_everything/math_.py
yppm/auto_everything/ml.py
yppm/auto_everything/monitor.py
yppm/auto_everything/my_email.py
yppm/auto_everything/network.py
yppm/auto_everything/python.py
yppm/auto_everything/string_.py
yppm/auto_everything/terminal.py
yppm/auto_everything/time.py
yppm/auto_everything/video.py
yppm/auto_everything/wallet.py
yppm/auto_everything/web.py
yppm/auto_everything/x11/build.py
yppm/auto_everything/x11/setup.py
yppm/auto_everything/x11/test.py
yppm/auto_everything/yingshaoxo_python/built_in_functions.py
yppm/resources/basic_python_project/main.py
yppm/resources/magic_magnet/Tools.py
yppm/resources/magic_magnet/app.py
yppm/resources/magic_magnet/auto_everything/__init__.py
yppm/resources/magic_magnet/auto_everything/__main__.py
yppm/resources/magic_magnet/auto_everything/_command_line_interface.py
yppm/resources/magic_magnet/auto_everything/all.py
yppm/resources/magic_magnet/auto_everything/audio.py
yppm/resources/magic_magnet/auto_everything/base.py
yppm/resources/magic_magnet/auto_everything/camera.py
yppm/resources/magic_magnet/auto_everything/cryptography.py
yppm/resources/magic_magnet/auto_everything/database.py
yppm/resources/magic_magnet/auto_everything/develop.py
yppm/resources/magic_magnet/auto_everything/disk.py
yppm/resources/magic_magnet/auto_everything/gui.py
yppm/resources/magic_magnet/auto_everything/http_.py
yppm-0.1.1.dist-info/LICENSE
yppm-0.1.1.dist-info/METADATA
yppm-0.1.1.dist-info/WHEEL
yppm-0.1.1.dist-info/top_level.txt
yppm-0.1.1.dist-info/RECORD
