Metadata-Version: 2.1
Name: yppm
Version: 0.1.1
Summary: Yingshaoxo Python Package Manager
Author-email: yingshaoxo <yingshaoxo@gmail.com>
Project-URL: Homepage, https://gitlab.com/yingshaoxo/yppm
Project-URL: Bug Tracker, https://gitlab.com/yingshaoxo/yppm/issues
Classifier: Programming Language :: Python :: 3
Classifier: License :: OSI Approved :: MIT License
Classifier: Operating System :: OS Independent
Requires-Python: >=3.10
License-File: LICENSE
